innoldb/__init__.py
innoldb/main.py
innoldb/qldb.py
innoldb/settings.py
innoldb/derivers/__init__.py
innoldb/static/__init__.py
innoldb/static/clauses.py
innoldb/static/driver.py
innoldb/static/logger.py
innoldb/static/objects.py
innoldb-1.0.15.dist-info/LICENSE
innoldb-1.0.15.dist-info/METADATA
innoldb-1.0.15.dist-info/WHEEL
innoldb-1.0.15.dist-info/entry_points.txt
innoldb-1.0.15.dist-info/top_level.txt
innoldb-1.0.15.dist-info/RECORD
