Metadata-Version: 2.1
Name: innoldb
Version: 1.0.15
Summary: a ORM model for AWS QLDB
Home-page: https://innolab-coverage.makpar-innovation.net
Author: Makpar Innovation Lab
Author-email: gmoore@makpar.com
License: GNU GPL v3
Project-URL: Documentation, https://makpar-innovation-laboratory.github.io/qldb-orm/
Project-URL: Source, https://github.com/Makpar-Innovation-Laboratory/qldb-orm
Keywords: aws,qldb,quantum-ledger-database,orm
Platform: any
Requires-Python: >=3.8
License-File: LICENSE
Requires-Dist: jsonconversion (>=0.2.13)
Requires-Dist: pyqldb (>=3.2.2)
Requires-Dist: python-dotenv (>=0.19.2)
